tests/__init__.py
tests/test_CLI.py
tests/test_YamlModel.py
tests/test_yaml2petab.py
tests/test_yaml2sbml.py
tests/test_yaml_validation.py
yaml2sbml/YamlModel.py
yaml2sbml/__init__.py
yaml2sbml/version.py
yaml2sbml/yaml2PEtab.py
yaml2sbml/yaml2sbml.py
yaml2sbml/yaml_schema.yaml
yaml2sbml/yaml_validation.py
yaml2sbml-0.2.5.dist-info/LICENSE
yaml2sbml-0.2.5.dist-info/METADATA
yaml2sbml-0.2.5.dist-info/WHEEL
yaml2sbml-0.2.5.dist-info/entry_points.txt
yaml2sbml-0.2.5.dist-info/top_level.txt
yaml2sbml-0.2.5.dist-info/RECORD
