Metadata-Version: 2.1
Name: yaml2sbml
Version: 0.2.5
Summary: A small package to convert ODEs specified in a YAML file to SBML/PEtab
Home-page: https://github.com/yaml2sbml-dev/yaml2sbml
Author: Jakob Vanhoefer, Marta R. A. Matos, Dilan Pathirana, Yannik Schälte
Author-email: jakob.vanhoefer@uni-bonn.de,marta.ra.matos@gmail.com
License: MIT
Download-URL: https://github.com/yaml2sbml-dev/yaml2sbml/releases
Project-URL: Bug Tracker, https://github.com/yaml2sbml-dev/yaml2sbml/issues
Project-URL: Documentation, https://yaml2sbml.readthedocs.io
Project-URL: Changelog, https://yaml2sbml.readthedocs.io/en/latest/release_notes.html
Keywords: YAML,SBML,PEtab,ODE
Platform: UNKNOWN
Classifier: Development Status :: 4 - Beta
Classifier: Environment :: Console
Classifier: Intended Audience :: Science/Research
Classifier: License :: OSI Approved :: MIT License
Classifier: Operating System :: OS Independent
Classifier: Programming Language :: Python
Classifier: Programming Language :: Python :: 3.9
Classifier: Programming Language :: Python :: 3.8
Classifier: Programming Language :: Python :: 3.7
Classifier: Programming Language :: Python :: 3.6
Requires-Python: >=3.6
Requires-Dist: pandas (>=1.0.1)
Requires-Dist: PyYAML (>=5.1)
Requires-Dist: python-libsbml (>=5.18.0)
Requires-Dist: petab (>=0.1.4)
Provides-Extra: doc
Requires-Dist: ipython (>=7.18.1) ; extra == 'doc'
Requires-Dist: nbconvert (>=6.0.7) ; extra == 'doc'
Requires-Dist: nbsphinx (>=0.8.0) ; extra == 'doc'
Requires-Dist: sphinx (>=3.4.3) ; extra == 'doc'
Requires-Dist: sphinx-rtd-theme (>=0.5.1) ; extra == 'doc'
Requires-Dist: sphinx-autodoc-typehints (>=1.11.1) ; extra == 'doc'
Provides-Extra: examples
Requires-Dist: amici (>=0.11.14) ; extra == 'examples'
Requires-Dist: matplotlib (>=3.1.0) ; extra == 'examples'
Requires-Dist: notebook (>=6.1.4) ; extra == 'examples'
Requires-Dist: numpy (>=1.19.4) ; extra == 'examples'
Requires-Dist: pypesto (>=0.2.3) ; extra == 'examples'
Requires-Dist: scipy (>=1.6.0) ; extra == 'examples'
